{
  "_B0uyGNpR.js": {
    "resourceType": "script",
    "module": true,
    "prefetch": true,
    "preload": true,
    "file": "B0uyGNpR.js",
    "name": "nuxt-link",
    "imports": [
      "node_modules/nuxt/dist/app/entry.js"
    ]
  },
  "_as5Msraf.js": {
    "resourceType": "script",
    "module": true,
    "prefetch": true,
    "preload": true,
    "file": "as5Msraf.js",
    "name": "v3",
    "imports": [
      "node_modules/nuxt/dist/app/entry.js"
    ]
  },
  "layouts/default.vue": {
    "resourceType": "script",
    "module": true,
    "prefetch": true,
    "preload": true,
    "file": "BLRXeD6V.js",
    "name": "default",
    "src": "layouts/default.vue",
    "isDynamicEntry": true,
    "imports": [
      "_B0uyGNpR.js",
      "node_modules/nuxt/dist/app/entry.js"
    ]
  },
  "node_modules/nuxt/dist/app/components/error-404.vue": {
    "resourceType": "script",
    "module": true,
    "prefetch": true,
    "preload": true,
    "file": "BPaTXrmm.js",
    "name": "error-404",
    "src": "node_modules/nuxt/dist/app/components/error-404.vue",
    "isDynamicEntry": true,
    "imports": [
      "_B0uyGNpR.js",
      "node_modules/nuxt/dist/app/entry.js",
      "_as5Msraf.js"
    ],
    "css": []
  },
  "error-404.DqZyKpgk.css": {
    "file": "error-404.DqZyKpgk.css",
    "resourceType": "style",
    "prefetch": true,
    "preload": true
  },
  "node_modules/nuxt/dist/app/components/error-500.vue": {
    "resourceType": "script",
    "module": true,
    "prefetch": true,
    "preload": true,
    "file": "BAWPQKSm.js",
    "name": "error-500",
    "src": "node_modules/nuxt/dist/app/components/error-500.vue",
    "isDynamicEntry": true,
    "imports": [
      "node_modules/nuxt/dist/app/entry.js",
      "_as5Msraf.js"
    ],
    "css": []
  },
  "error-500.CZqNkBuR.css": {
    "file": "error-500.CZqNkBuR.css",
    "resourceType": "style",
    "prefetch": true,
    "preload": true
  },
  "node_modules/nuxt/dist/app/entry.js": {
    "resourceType": "script",
    "module": true,
    "prefetch": true,
    "preload": true,
    "file": "BagzlX2Y.js",
    "name": "entry",
    "src": "node_modules/nuxt/dist/app/entry.js",
    "isEntry": true,
    "dynamicImports": [
      "layouts/default.vue",
      "node_modules/nuxt/dist/app/components/error-404.vue",
      "node_modules/nuxt/dist/app/components/error-500.vue"
    ],
    "_globalCSS": true
  },
  "pages/about.vue": {
    "resourceType": "script",
    "module": true,
    "prefetch": true,
    "preload": true,
    "file": "j2q_rHCT.js",
    "name": "about",
    "src": "pages/about.vue",
    "isDynamicEntry": true,
    "imports": [
      "_as5Msraf.js",
      "node_modules/nuxt/dist/app/entry.js"
    ]
  },
  "pages/index.vue": {
    "resourceType": "script",
    "module": true,
    "prefetch": true,
    "preload": true,
    "file": "DNk_HXp8.js",
    "name": "index",
    "src": "pages/index.vue",
    "isDynamicEntry": true,
    "imports": [
      "node_modules/nuxt/dist/app/entry.js",
      "_as5Msraf.js"
    ],
    "css": [],
    "assets": [
      "pro.DZ6561Fe.png",
      "wow-icon-2.DHIKvl6a.png"
    ]
  },
  "index.B8OaXHgK.css": {
    "file": "index.B8OaXHgK.css",
    "resourceType": "style",
    "prefetch": true,
    "preload": true
  },
  "pro.DZ6561Fe.png": {
    "file": "pro.DZ6561Fe.png",
    "resourceType": "image",
    "prefetch": true,
    "mimeType": "image/png"
  },
  "wow-icon-2.DHIKvl6a.png": {
    "file": "wow-icon-2.DHIKvl6a.png",
    "resourceType": "image",
    "prefetch": true,
    "mimeType": "image/png"
  },
  "pages/projects.vue": {
    "resourceType": "script",
    "module": true,
    "prefetch": true,
    "preload": true,
    "file": "B1mI63Jx.js",
    "name": "projects",
    "src": "pages/projects.vue",
    "isDynamicEntry": true,
    "imports": [
      "node_modules/nuxt/dist/app/entry.js",
      "_as5Msraf.js"
    ]
  },
  "pro.png": {
    "resourceType": "image",
    "prefetch": true,
    "mimeType": "image/png",
    "file": "pro.DZ6561Fe.png",
    "src": "pro.png"
  },
  "wow-icon-2.png": {
    "resourceType": "image",
    "prefetch": true,
    "mimeType": "image/png",
    "file": "wow-icon-2.DHIKvl6a.png",
    "src": "wow-icon-2.png"
  }
}